clearutils/__init__.py
clearutils/backup.py
clearutils/fetch.py
clearutils/format.py
clearutils/log.py
clearutils/test.py
clearutils-0.1.0.dist-info/licenses/LICENSE
clearutils-0.1.0.dist-info/METADATA
clearutils-0.1.0.dist-info/WHEEL
clearutils-0.1.0.dist-info/top_level.txt
clearutils-0.1.0.dist-info/RECORD
