Metadata-Version: 2.4
Name: clearutils
Version: 0.1.0
Summary: A collection of clear, modular helpers for testing, logging, formatting, and more.
Author-email: Renya Wasson <renya.wasson@gmail.com>
License: MIT License
Requires-Python: >=3.11
License-File: LICENSE
Requires-Dist: numpy
Requires-Dist: pandas
Dynamic: license-file
